altair_tiles/__init__.py
altair_tiles/py.typed
altair_tiles-0.2.0.dist-info/METADATA
altair_tiles-0.2.0.dist-info/WHEEL
altair_tiles-0.2.0.dist-info/licenses/LICENSE
altair_tiles-0.2.0.dist-info/RECORD
