Metadata-Version: 2.1
Name: altair_tiles
Version: 0.2.0
Summary: altair_tiles
Project-URL: Source, https://github.com/altair-viz/altair_tiles
Author: altair_tiles contributors
License-File: LICENSE
Keywords: altair,basemaps,tiles
Classifier: License :: OSI Approved :: BSD License
Classifier: Natural Language :: English
Classifier: Programming Language :: Python :: 3.9
Classifier: Programming Language :: Python :: 3.10
Classifier: Programming Language :: Python :: 3.11
Classifier: Programming Language :: Python :: 3.12
Classifier: Typing :: Typed
Requires-Python: >=3.9
Requires-Dist: altair
Requires-Dist: mercantile
Requires-Dist: xyzservices
Provides-Extra: dev
Requires-Dist: geopandas; extra == 'dev'
Requires-Dist: ghp-import; extra == 'dev'
Requires-Dist: hatch; extra == 'dev'
Requires-Dist: ipykernel; extra == 'dev'
Requires-Dist: ipython; extra == 'dev'
Requires-Dist: mypy; extra == 'dev'
Requires-Dist: pytest; extra == 'dev'
Requires-Dist: ruff>=0.1.4; extra == 'dev'
Requires-Dist: vega-datasets; extra == 'dev'
Requires-Dist: vl-convert-python; extra == 'dev'
Provides-Extra: doc
Requires-Dist: jupyter-book; extra == 'doc'
Requires-Dist: vl-convert-python; extra == 'doc'
